LICENSE
README.md
pyemtvlc
setup.py
pyemtvlc.egg-info/PKG-INFO
pyemtvlc.egg-info/SOURCES.txt
pyemtvlc.egg-info/dependency_links.txt
pyemtvlc.egg-info/requires.txt
pyemtvlc.egg-info/top_level.txt
test/__init__.py
test/test_outs.py
test/test_parser.py
test/test_parser_mock.py
utils/__init__.py
utils/emtinfo.py
utils/parser.py