Metadata-Version: 2.4
Name: pyemtvlc
Version: 0.3.6
Summary: Python package to query  EMT Valencia (bus).
Home-page: https://github.com/andoniaf/pyemtvlc
Author: Andoni Alonso F.
Author-email: andonialonsof@gmail.com
Classifier: Programming Language :: Python :: 3
Classifier: License :: OSI Approved :: GNU General Public License v3 or later (GPLv3+)
Classifier: Operating System :: OS Independent
License-File: LICENSE
Requires-Dist: requests
Requires-Dist: beautifulsoup4
Dynamic: author
Dynamic: author-email
Dynamic: classifier
Dynamic: description
Dynamic: description-content-type
Dynamic: home-page
Dynamic: license-file
Dynamic: requires-dist
Dynamic: summary
